a_pandas_ex_drop_duplicates_without_pain/LICENSE
a_pandas_ex_drop_duplicates_without_pain/README.MD
a_pandas_ex_drop_duplicates_without_pain/__init__.py
a_pandas_ex_drop_duplicates_without_pain/requirements.txt
a_pandas_ex_drop_duplicates_without_pain/thirdparty.json
a_pandas_ex_drop_duplicates_without_pain-0.12.dist-info/LICENSE.rst
a_pandas_ex_drop_duplicates_without_pain-0.12.dist-info/METADATA
a_pandas_ex_drop_duplicates_without_pain-0.12.dist-info/WHEEL
a_pandas_ex_drop_duplicates_without_pain-0.12.dist-info/top_level.txt
a_pandas_ex_drop_duplicates_without_pain-0.12.dist-info/RECORD
