Metadata-Version: 2.1
Name: a-pandas-ex-drop-duplicates-without-pain
Version: 0.12
Summary: Some useful methods for columns / index in Pandas DataFrames
Home-page: https://github.com/hansalemaos/a_pandas_ex_drop_duplicates_without_pain
Author: Johannes Fischer
Author-email: <aulasparticularesdealemaosp@gmail.com>
License: MIT
Keywords: pandas,numpy,dataframe,series
Classifier: Development Status :: 4 - Beta
Classifier: Programming Language :: Python :: 3 :: Only
Classifier: Programming Language :: Python :: 3.9
Classifier: Topic :: Scientific/Engineering :: Visualization
Classifier: Topic :: Software Development :: Libraries :: Python Modules
Classifier: Topic :: Text Editors :: Text Processing
Classifier: Topic :: Text Processing :: General
Classifier: Topic :: Text Processing :: Indexing
Classifier: Topic :: Text Processing :: Filters
Classifier: Topic :: Utilities
License-File: LICENSE.rst
Requires-Dist: a-pandas-ex-plode-tool
Requires-Dist: pandas
